deskew_tool/__init__.py
deskew_tool/deskew_pdf.py
pdf_deskew_ui/__init__.py
pdf_deskew_ui/main.py
pdf_deskew_ui/ui.py
pdf_deskew_ui/worker.py
pdf_deskew-0.1.8.dist-info/METADATA
pdf_deskew-0.1.8.dist-info/WHEEL
pdf_deskew-0.1.8.dist-info/entry_points.txt
pdf_deskew-0.1.8.dist-info/licenses/LICENSE
pdf_deskew-0.1.8.dist-info/RECORD
