Metadata-Version: 2.4
Name: pdf-deskew
Version: 0.1.8
Summary: A GUI tool for deskewing scanned PDF documents using PyQt6 and OpenCV
Project-URL: Homepage, https://github.com/Tinnci/pdf_deskew
Project-URL: Repository, https://github.com/Tinnci/pdf_deskew.git
Project-URL: Issues, https://github.com/Tinnci/pdf_deskew/issues
Author-email: driezy <luoyido@outlook.com>
License: MIT
License-File: LICENSE
Keywords: deskew,gui,image-processing,opencv,pdf,pyqt6
Classifier: Development Status :: 3 - Alpha
Classifier: Environment :: X11 Applications :: Qt
Classifier: Intended Audience :: End Users/Desktop
Classifier: License :: OSI Approved :: MIT License
Classifier: Natural Language :: Chinese (Simplified)
Classifier: Natural Language :: English
Classifier: Operating System :: OS Independent
Classifier: Programming Language :: Python
Classifier: Programming Language :: Python :: 3
Classifier: Programming Language :: Python :: 3.12
Classifier: Programming Language :: Python :: 3.13
Classifier: Topic :: Multimedia :: Graphics :: Viewers
Classifier: Topic :: Office/Business
Requires-Python: >=3.12
Requires-Dist: deskew>=1.5.1
Requires-Dist: numpy>=2.1.2
Requires-Dist: opencv-python>=4.10.0.84
Requires-Dist: pillow>=11.0.0
Requires-Dist: pymupdf>=1.24.13
Requires-Dist: pyqt6>=6.7.1
Requires-Dist: qt-material>=2.14
Requires-Dist: tqdm>=4.66.6
